aft/__init__.py
aft/__main__.py
aft/fuzzer.py
aft/instances.py
aft-0.1.2.dist-info/LICENSE
aft-0.1.2.dist-info/METADATA
aft-0.1.2.dist-info/WHEEL
aft-0.1.2.dist-info/entry_points.txt
aft-0.1.2.dist-info/top_level.txt
aft-0.1.2.dist-info/RECORD
