Metadata-Version: 2.1
Name: aft
Version: 0.1.2
Summary: Rabbit Type inference for Python
Home-page: https://github.com/strawberry-jam-cabal/aft
Author: Annie Cherkaev, Tobin Yehle, and Nic Bertagnolli
Author-email: strawberry.jam.cabal@gmail.com
License: UNKNOWN
Platform: UNKNOWN
Classifier: Programming Language :: Python :: 3
Classifier: License :: OSI Approved :: MIT License
Classifier: Operating System :: OS Independent
Classifier: Environment :: Console
Classifier: Intended Audience :: Developers
Classifier: Topic :: Software Development
Requires-Dist: typing
Requires-Dist: funcsigs
